odoo/addons/sale_order_minimum_amount/README.rst
odoo/addons/sale_order_minimum_amount/__init__.py
odoo/addons/sale_order_minimum_amount/__manifest__.py
odoo/addons/sale_order_minimum_amount/i18n/sale_order_minimum_amount.pot
odoo/addons/sale_order_minimum_amount/models/__init__.py
odoo/addons/sale_order_minimum_amount/models/res_company.py
odoo/addons/sale_order_minimum_amount/models/res_config_settings.py
odoo/addons/sale_order_minimum_amount/models/sale_order.py
odoo/addons/sale_order_minimum_amount/readme/CONFIGURE.rst
odoo/addons/sale_order_minimum_amount/readme/CONTRIBUTORS.rst
odoo/addons/sale_order_minimum_amount/readme/CREDITS.rst
odoo/addons/sale_order_minimum_amount/readme/DESCRIPTION.rst
odoo/addons/sale_order_minimum_amount/readme/USAGE.rst
odoo/addons/sale_order_minimum_amount/static/description/icon.png
odoo/addons/sale_order_minimum_amount/static/description/index.html
odoo/addons/sale_order_minimum_amount/tests/__init__.py
odoo/addons/sale_order_minimum_amount/tests/test_sale_order.py
odoo/addons/sale_order_minimum_amount/views/res_config_settings_views.xml
odoo_addon_sale_order_minimum_amount-16.0.1.0.0.2.dist-info/METADATA
odoo_addon_sale_order_minimum_amount-16.0.1.0.0.2.dist-info/WHEEL
odoo_addon_sale_order_minimum_amount-16.0.1.0.0.2.dist-info/top_level.txt
odoo_addon_sale_order_minimum_amount-16.0.1.0.0.2.dist-info/RECORD
