Metadata-Version: 2.1
Name: odoo-addon-sale_order_minimum_amount
Version: 16.0.1.0.0.2
Summary: Restrict confirmation of sales orders below a configured minimum total amount
Home-page: https://github.com/OCA/sale-workflow
Author: BizzAppDev Systems Pvt. Ltd., Odoo Community Association (OCA)
Author-email: support@odoo-community.org
License: AGPL-3
Classifier: Programming Language :: Python
Classifier: Framework :: Odoo
Classifier: Framework :: Odoo :: 16.0
Classifier: License :: OSI Approved :: GNU Affero General Public License v3
Classifier: Development Status :: 3 - Alpha
Requires-Python: >=3.10
Requires-Dist: odoo<16.1dev,>=16.0a
